README.rst
setup.cfg
setup.py
django_goodforms.egg-info/PKG-INFO
django_goodforms.egg-info/SOURCES.txt
django_goodforms.egg-info/dependency_links.txt
django_goodforms.egg-info/requires.txt
django_goodforms.egg-info/top_level.txt
goodforms/__init__.py
goodforms/settings.py
goodforms/tests.py
goodforms/templatetags/__init__.py
goodforms/templatetags/form_fields.py