Metadata-Version: 1.1
Name: django-goodforms
Version: 0.2.1
Summary: Custom renderer for django form fields
Home-page: https://github.com/zenwalker/django-goodforms
Author: Maxim Poletaev
Author-email: max.poletaev@gmail.com
License: BSD
Keywords: django forms
Platform: UNKNOWN
Classifier: Development Status :: 4 - Beta
Classifier: Programming Language :: Python :: 3.3
Classifier: Programming Language :: Python :: 3.4
Classifier: Programming Language :: Python :: 3.5
Classifier: Framework :: Django :: 1.8
Classifier: Framework :: Django :: 1.9
